mcp_web_browser/__init__.py
mcp_web_browser/config.py
mcp_web_browser/server.py
mcp_web_browser/uvx_config.py
web_browser_mcp-0.1.1.dist-info/METADATA
web_browser_mcp-0.1.1.dist-info/WHEEL
web_browser_mcp-0.1.1.dist-info/entry_points.txt
web_browser_mcp-0.1.1.dist-info/licenses/LICENSE
web_browser_mcp-0.1.1.dist-info/RECORD
