Metadata-Version: 2.3
Name: web-browser-mcp
Version: 0.1.1
Summary: Transform your AI applications with advanced web browsing capabilities through this Model Context Protocol (MCP) server
Project-URL: Repository, https://github.com/blazickjp/web-browser-mcp-server
License: MIT
Requires-Python: >=3.11
Requires-Dist: aiohttp==3.9.1
Requires-Dist: beautifulsoup4==4.12.2
Requires-Dist: click==8.1.7
Requires-Dist: fastapi==0.109.0
Requires-Dist: mcp>=0.9.1
Requires-Dist: pydantic-settings==2.1.0
Requires-Dist: pydantic==2.6.0
Requires-Dist: python-dotenv==1.0.0
Requires-Dist: requests==2.31.0
Requires-Dist: uvicorn==0.27.0
Provides-Extra: test
Requires-Dist: aioresponses==0.7.6; extra == 'test'
Requires-Dist: httpx==0.26.0; extra == 'test'
Requires-Dist: pluggy==1.3.0; extra == 'test'
Requires-Dist: pytest-asyncio==0.23.5; extra == 'test'
Requires-Dist: pytest-cov==4.1.0; extra == 'test'
Requires-Dist: pytest==8.0.0; extra == 'test'
